lofarSun/__init__.py
lofarSun/lofarData.py
lofarSun/lofarJ2000xySun.py
lofarSun-0.1.6.dist-info/LICENSE.txt
lofarSun-0.1.6.dist-info/METADATA
lofarSun-0.1.6.dist-info/WHEEL
lofarSun-0.1.6.dist-info/top_level.txt
lofarSun-0.1.6.dist-info/RECORD
