Metadata-Version: 2.1
Name: lofarSun
Version: 0.1.6
Summary: tools to process the lofar solar data
Home-page: https://github.com/Pjer-zhang/LOFAR_Solar
Author: Peijin
Author-email: pjer1316@gmail.com
License: MIT
Download-URL: https://github.com/Pjer-zhang/LOFAR_Solar/archive/master.zip
Keywords: LOFAR,Solar,radio
Platform: UNKNOWN
Classifier: Development Status :: 3 - Alpha
Classifier: Intended Audience :: Developers
Classifier: Topic :: Software Development :: Build Tools
Classifier: License :: OSI Approved :: MIT License
Classifier: Programming Language :: Python :: 3.6
Classifier: Programming Language :: Python :: 3.7
Requires-Dist: matplotlib
Requires-Dist: sunpy
Requires-Dist: opencv-python
Requires-Dist: astropy
